opmanager_mcp/__init__.py
opmanager_mcp/api_client.py
opmanager_mcp/config.py
opmanager_mcp/exceptions.py
opmanager_mcp/http_server.py
opmanager_mcp/logging_config.py
opmanager_mcp/main.py
opmanager_mcp/server.py
opmanager_mcp/tool_generator.py
opmanager_mcp_server-1.0.0.dist-info/METADATA
opmanager_mcp_server-1.0.0.dist-info/WHEEL
opmanager_mcp_server-1.0.0.dist-info/entry_points.txt
opmanager_mcp_server-1.0.0.dist-info/licenses/LICENSE
opmanager_mcp_server-1.0.0.dist-info/RECORD
