Metadata-Version: 2.4
Name: opmanager-mcp-server
Version: 1.0.0
Summary: Model Context Protocol (MCP) server for ManageEngine OpManager API integration
Project-URL: Homepage, https://github.com/sachdev27/opmanager-mcp-server
Project-URL: Documentation, https://github.com/sachdev27/opmanager-mcp-server#readme
Project-URL: Repository, https://github.com/sachdev27/opmanager-mcp-server.git
Project-URL: Issues, https://github.com/sachdev27/opmanager-mcp-server/issues
Project-URL: Changelog, https://github.com/sachdev27/opmanager-mcp-server/blob/main/CHANGELOG.md
Author: OpManager MCP Server Contributors
Maintainer: OpManager MCP Server Contributors
License: MIT
License-File: LICENSE
Keywords: ai,api,automation,claude,llm,manageengine,mcp,model-context-protocol,network-monitoring,opmanager
Classifier: Development Status :: 4 - Beta
Classifier: Intended Audience :: Developers
Classifier: Intended Audience :: System Administrators
Classifier: License :: OSI Approved :: MIT License
Classifier: Operating System :: OS Independent
Classifier: Programming Language :: Python :: 3
Classifier: Programming Language :: Python :: 3.10
Classifier: Programming Language :: Python :: 3.11
Classifier: Programming Language :: Python :: 3.12
Classifier: Topic :: Software Development :: Libraries :: Python Modules
Classifier: Topic :: System :: Monitoring
Classifier: Topic :: System :: Networking :: Monitoring
Classifier: Typing :: Typed
Requires-Python: >=3.10
Requires-Dist: httpx>=0.25.0
Requires-Dist: mcp>=1.0.0
Requires-Dist: pydantic-settings>=2.0.0
Requires-Dist: pydantic>=2.0.0
Requires-Dist: python-dotenv>=1.0.0
Requires-Dist: pyyaml>=6.0
Provides-Extra: all
Requires-Dist: black>=23.0.0; extra == 'all'
Requires-Dist: isort>=5.12.0; extra == 'all'
Requires-Dist: mkdocs-material>=9.0.0; extra == 'all'
Requires-Dist: mkdocs>=1.5.0; extra == 'all'
Requires-Dist: mkdocstrings[python]>=0.24.0; extra == 'all'
Requires-Dist: mypy>=1.0.0; extra == 'all'
Requires-Dist: pre-commit>=3.0.0; extra == 'all'
Requires-Dist: pytest-asyncio>=0.21.0; extra == 'all'
Requires-Dist: pytest-cov>=4.0.0; extra == 'all'
Requires-Dist: pytest-mock>=3.10.0; extra == 'all'
Requires-Dist: pytest>=7.0.0; extra == 'all'
Requires-Dist: respx>=0.20.0; extra == 'all'
Requires-Dist: ruff>=0.1.0; extra == 'all'
Requires-Dist: sse-starlette>=1.6.0; extra == 'all'
Requires-Dist: starlette>=0.32.0; extra == 'all'
Requires-Dist: uvicorn>=0.24.0; extra == 'all'
Provides-Extra: dev
Requires-Dist: black>=23.0.0; extra == 'dev'
Requires-Dist: isort>=5.12.0; extra == 'dev'
Requires-Dist: mypy>=1.0.0; extra == 'dev'
Requires-Dist: pre-commit>=3.0.0; extra == 'dev'
Requires-Dist: pytest-asyncio>=0.21.0; extra == 'dev'
Requires-Dist: pytest-cov>=4.0.0; extra == 'dev'
Requires-Dist: pytest-mock>=3.10.0; extra == 'dev'
Requires-Dist: pytest>=7.0.0; extra == 'dev'
Requires-Dist: respx>=0.20.0; extra == 'dev'
Requires-Dist: ruff>=0.1.0; extra == 'dev'
Provides-Extra: docs
Requires-Dist: mkdocs-material>=9.0.0; extra == 'docs'
Requires-Dist: mkdocs>=1.5.0; extra == 'docs'
Requires-Dist: mkdocstrings[python]>=0.24.0; extra == 'docs'
Provides-Extra: http
Requires-Dist: sse-starlette>=1.6.0; extra == 'http'
Requires-Dist: starlette>=0.32.0; extra == 'http'
Requires-Dist: uvicorn>=0.24.0; extra == 'http'
